wrdata/__init__.py
wrdata/stream.py
wrdata/core/__init__.py
wrdata/core/config.py
wrdata/models/__init__.py
wrdata/models/database.py
wrdata/models/schemas.py
wrdata/providers/__init__.py
wrdata/providers/alpaca_provider.py
wrdata/providers/alphavantage_provider.py
wrdata/providers/base.py
wrdata/providers/binance_provider.py
wrdata/providers/bitfinex_provider.py
wrdata/providers/bybit_provider.py
wrdata/providers/ccxt_provider.py
wrdata/providers/coinbase_advanced_provider.py
wrdata/providers/coinbase_provider.py
wrdata/providers/coingecko_provider.py
wrdata/providers/cryptocompare_provider.py
wrdata/providers/deribit_provider.py
wrdata/providers/dexscreener_provider.py
wrdata/providers/finnhub_provider.py
wrdata/providers/fred_provider.py
wrdata/providers/gateio_provider.py
wrdata/providers/geckoterminal_provider.py
wrdata/providers/gemini_provider.py
wrdata/providers/huobi_provider.py
wrdata/providers/ibkr_provider.py
wrdata/providers/iexcloud_provider.py
wrdata/providers/kalshi_provider.py
wrdata/providers/kraken_provider.py
wrdata/providers/kucoin_provider.py
wrdata/providers/marketstack_provider.py
wrdata/providers/messari_provider.py
wrdata/providers/okx_provider.py
wrdata/providers/polygon_provider.py
wrdata/providers/tdameritrade_provider.py
wrdata/providers/tiingo_provider.py
wrdata/providers/tradier_provider.py
wrdata/providers/twelvedata_provider.py
wrdata/providers/whale_alert_provider.py
wrdata/providers/yfinance_provider.py
wrdata/services/__init__.py
wrdata/services/options_fetcher.py
wrdata/services/symbol_discovery.py
wrdata/services/symbol_manager.py
wrdata/streaming/__init__.py
wrdata/streaming/alpaca_stream.py
wrdata/streaming/base.py
wrdata/streaming/binance_stream.py
wrdata/streaming/coinbase_stream.py
wrdata/streaming/finnhub_stream.py
wrdata/streaming/ibkr_stream.py
wrdata/streaming/kraken_stream.py
wrdata/streaming/manager.py
wrdata/streaming/polygon_stream.py
wrdata/streaming/whale_alert_stream.py
wrdata/utils/__init__.py
wrdata-0.1.2.dist-info/licenses/LICENSE
wrdata-0.1.2.dist-info/METADATA
wrdata-0.1.2.dist-info/WHEEL
wrdata-0.1.2.dist-info/top_level.txt
wrdata-0.1.2.dist-info/RECORD
