Metadata-Version: 2.4
Name: wrdata
Version: 0.1.2
Summary: WR Data - Universal data gathering package for financial and market data
Author-email: Wayy Research <research@wayy.com>
License: MIT
Project-URL: Homepage, https://github.com/wayy-research/wrdata
Project-URL: Documentation, https://github.com/wayy-research/wrdata
Project-URL: Repository, https://github.com/wayy-research/wrdata
Keywords: finance,data,market-data,crypto,stocks,forex
Classifier: Development Status :: 3 - Alpha
Classifier: Intended Audience :: Developers
Classifier: Topic :: Office/Business :: Financial
Classifier: License :: OSI Approved :: MIT License
Classifier: Programming Language :: Python :: 3
Classifier: Programming Language :: Python :: 3.11
Requires-Python: >=3.10
License-File: LICENSE
Requires-Dist: requests>=2.31.0
Requires-Dist: pandas>=2.0.0
Requires-Dist: polars>=0.20.0
Requires-Dist: pydantic>=2.6.0
Requires-Dist: pydantic-settings>=2.0.0
Requires-Dist: python-dotenv>=1.0.0
Requires-Dist: sqlalchemy>=2.0.0
Requires-Dist: ccxt>=4.0.0
Requires-Dist: yfinance>=0.2.0
Provides-Extra: dev
Requires-Dist: pytest>=7.0.0; extra == "dev"
Requires-Dist: black>=23.0.0; extra == "dev"
Requires-Dist: ruff>=0.1.0; extra == "dev"
Requires-Dist: mypy>=1.0.0; extra == "dev"
Dynamic: license-file
